[
    {
        "Author": "Aireil",
        "Name": "FF Logs Viewer",
        "Punchline": "View FF Logs ranking percentiles in-game.",
        "Description": "View FF Logs ranking percentiles in-game. Add a context menu to open someone's logs. Layout, style, stats, default metric, and more are all customizable in the settings.",
        "Changelog": "-2.2.2.2\n    Switch default swap of ACC to Cruiserweight.\n-2.2.2.1\n    Default layout update + 7.2 update.",
        "InternalName": "FFLogsViewer",
        "AssemblyVersion": "2.2.2.2",
        "RepoUrl": "https://github.com/Aireil/FFLogsViewer",
        "ApplicableVersion": "any",
        "Tags": [
            "FFLogs"
        ],
        "DalamudApiLevel": 12,
        "IconUrl": "https://github.com/Aireil/FFLogsViewer/raw/master/res/icon.png",
        "ImageUrls": [
            "https://github.com/Aireil/FFLogsViewer/raw/master/res/image1.png",
            "https://github.com/Aireil/FFLogsViewer/raw/master/res/image2.png"
        ],
        "DownloadLinkInstall": "https://github.com/Aireil/MyDalamudPlugins/raw/master/plugins/FFLogsViewer/latest.zip",
        "IsHide": false,
        "IsTestingExclusive": false,
        "DownloadLinkTesting": "https://github.com/Aireil/MyDalamudPlugins/raw/master/plugins/FFLogsViewer/latest.zip",
        "DownloadLinkUpdate": "https://github.com/Aireil/MyDalamudPlugins/raw/master/plugins/FFLogsViewer/latest.zip",
        "DownloadCount": 0,
        "LastUpdate": "1750339347"
    },
    {
        "Author": "Aireil",
        "Name": "Forked Localization Fix",
        "Punchline": "Fixes in/out cast names in French and German for the last boss of The Forked Tower.",
        "Description": "Fixes in/out cast names in French and German for the last boss of The Forked Tower. No configuration, it just works. It will automatically disable itself on any game update.",
        "InternalName": "ForkedLocalizationFix",
        "AssemblyVersion": "0.0.0.4",
        "ApplicableVersion": "any",
        "DalamudApiLevel": 12,
        "DownloadLinkInstall": "https://github.com/Aireil/MyDalamudPlugins/raw/master/plugins/ForkedLocalizationFix/latest.zip",
        "IsHide": false,
        "IsTestingExclusive": false,
        "DownloadLinkTesting": "https://github.com/Aireil/MyDalamudPlugins/raw/master/plugins/ForkedLocalizationFix/latest.zip",
        "DownloadLinkUpdate": "https://github.com/Aireil/MyDalamudPlugins/raw/master/plugins/ForkedLocalizationFix/latest.zip",
        "DownloadCount": 0,
        "LastUpdate": "1750339347"
    }
]